lib/melcloud/__init__.py
lib/melcloud/devices.py
lib/melcloud/jsongenerator.py
lib/melcloud/melcloudclient.py
asyncio_melcloud_lib-1.0.0.dist-info/METADATA
asyncio_melcloud_lib-1.0.0.dist-info/WHEEL
asyncio_melcloud_lib-1.0.0.dist-info/RECORD
