Metadata-Version: 2.1
Name: asyncio-melcloud-lib
Version: 1.0.0
Summary: A async client for interacting with the MELCloud API
License: MIT
Author: Simen Andrè Vikestrand Skogum
Author-email: v0nNemize@gmail.com
Requires-Python: >=3.12,<4.0
Classifier: License :: OSI Approved :: MIT License
Classifier: Programming Language :: Python :: 3
Classifier: Programming Language :: Python :: 3.12
Requires-Dist: aiohttp (>=3.10.5,<4.0.0)
